randomness.py
randomness/__init__.py
randomness/__main__.py
randomness/_version.py
randomness/providers.py
randomness-0.2.1.dist-info/LICENSE
randomness-0.2.1.dist-info/METADATA
randomness-0.2.1.dist-info/WHEEL
randomness-0.2.1.dist-info/top_level.txt
randomness-0.2.1.dist-info/zip-safe
randomness-0.2.1.dist-info/RECORD
