Metadata-Version: 2.1
Name: randomness
Version: 0.2.1
Summary: Provide several randomness sources in Python with a common API
Home-page: https://github.com/blubberdiblub/randomness
Author: Niels Boehm
Author-email: blubberdiblub@gmail.com
License: MIT
Project-URL: Source, https://github.com/blubberdiblub/randomness
Project-URL: Tracker, https://github.com/blubberdiblub/randomness/issues
Keywords: randomness,random,RNG,entropy
Platform: UNKNOWN
Classifier: Development Status :: 3 - Alpha
Classifier: Intended Audience :: Developers
Classifier: Intended Audience :: Science/Research
Classifier: License :: OSI Approved :: MIT License
Classifier: Operating System :: OS Independent
Classifier: Programming Language :: Python
Classifier: Programming Language :: Python :: 3
Classifier: Programming Language :: Python :: 3 :: Only
Classifier: Programming Language :: Python :: 3.6
Classifier: Programming Language :: Python :: 3.7
Classifier: Topic :: Scientific/Engineering
Classifier: Topic :: Scientific/Engineering :: Mathematics
Classifier: Topic :: Software Development
Classifier: Topic :: Software Development :: Libraries
Classifier: Topic :: Software Development :: Libraries :: Python Modules
Requires-Python: >=3.6
Provides-Extra: rdrand
Requires-Dist: rdrand; extra == 'rdrand'
Provides-Extra: test
Requires-Dist: pytest; extra == 'test'
